README
ez_setup.py
setup.py
DAG.egg-info/PKG-INFO
DAG.egg-info/SOURCES.txt
DAG.egg-info/dependency_links.txt
DAG.egg-info/top_level.txt
dag/__init__.py
